CHANGELOG.md
LICENSE
tiktok_bot/__init__.py
tiktok_bot/api/__init__.py
tiktok_bot/api/api.py
tiktok_bot/api/config.py
tiktok_bot/bot/__init__.py
tiktok_bot/bot/bot.py
tiktok_bot/client/__init__.py
tiktok_bot/client/client.py
tiktok_bot/client/utils.py
tiktok_bot/models/__init__.py
tiktok_bot/models/category.py
tiktok_bot/models/comment.py
tiktok_bot/models/feed.py
tiktok_bot/models/feed_enums.py
tiktok_bot/models/follow.py
tiktok_bot/models/follower.py
tiktok_bot/models/hashtag.py
tiktok_bot/models/like.py
tiktok_bot/models/login.py
tiktok_bot/models/music.py
tiktok_bot/models/post.py
tiktok_bot/models/qr-code.py
tiktok_bot/models/request.py
tiktok_bot/models/search.py
tiktok_bot/models/sticker.py
tiktok_bot/models/tag.py
tiktok_bot/models/user.py
tiktok_bot/models/video.py
tiktok_bot-0.6.4.dist-info/LICENSE
tiktok_bot-0.6.4.dist-info/WHEEL
tiktok_bot-0.6.4.dist-info/METADATA
tiktok_bot-0.6.4.dist-info/RECORD
