Metadata-Version: 2.1
Name: tiktok-bot
Version: 0.6.4
Summary: Tik Tok API
Home-page: https://github.com/sudoguy/tiktok_bot/
License: MIT
Keywords: tiktok,bot,api,wrapper,tiktokbot
Author: Evgeny Kemerov
Author-email: eskemerov@gmail.com
Requires-Python: >=3.6,<4.0
Classifier: Development Status :: 3 - Alpha
Classifier: Environment :: Console
Classifier: Intended Audience :: End Users/Desktop
Classifier: Intended Audience :: Information Technology
Classifier: Intended Audience :: Science/Research
Classifier: License :: OSI Approved :: MIT License
Classifier: Operating System :: OS Independent
Classifier: Programming Language :: Python :: 3
Classifier: Programming Language :: Python :: 3.6
Classifier: Programming Language :: Python :: 3.7
Classifier: Programming Language :: Python :: 3.8
Classifier: Topic :: Software Development :: Libraries :: Python Modules
Requires-Dist: httpx (>=0.7.4,<0.8.0)
Requires-Dist: loguru (>=0.3.2,<0.4.0)
Requires-Dist: pydantic (>=0.32.2,<0.33.0)
Requires-Dist: tqdm (>=4.38.0,<5.0.0)
Requires-Dist: typing-extensions (>=3.7.4,<4.0.0)
Project-URL: Repository, https://github.com/sudoguy/tiktok_bot/
